LICENSE
MANIFEST.in
README.md
setup.py
django_trace/__init__.py
django_trace/admin.py
django_trace/controller.py
django_trace/middleware.py
django_trace/models.py
django_trace/trace_views.py
django_trace/urls.py
django_trace.egg-info/PKG-INFO
django_trace.egg-info/SOURCES.txt
django_trace.egg-info/dependency_links.txt
django_trace.egg-info/not-zip-safe
django_trace.egg-info/requires.txt
django_trace.egg-info/top_level.txt
django_trace/management/__init__.py
django_trace/management/commands/__init__.py
django_trace/management/commands/check_resources.py
django_trace/migrations/0001_initial.py
django_trace/migrations/__init__.py
django_trace/static/django_trace/audit.js
django_trace/static/django_trace/jquery-3.7.1.min.js
django_trace/static/django_trace/select2.min.css
django_trace/static/django_trace/select2.min.js
django_trace/templates/audit.html
django_trace/templates/audit_with_base.html