Metadata-Version: 2.1
Name: django_trace
Version: 2.0.2
Summary: django_trace is a python package for monitoring your django web app
Home-page: https://github.com/kouroshparsa/django_trace
Download-URL: https://github.com/kouroshparsa/django_trace/packages/2.0.2
Author: Kourosh Parsa
Author-email: kouroshtheking@gmail.com
License: GNU
Classifier: Programming Language :: Python
Requires-Python: >=2.7
License-File: LICENSE
Requires-Dist: django>=1.8
Requires-Dist: django-autocomplete-light>=3.8
